archaeo_mag/__init__.py
archaeo_mag/depth_estimation.py
archaeo_mag/pre_processing_functions.py
archaeo_mag/raster_functions.py
archaeo_mag-0.0.1.dist-info/LICENSE
archaeo_mag-0.0.1.dist-info/METADATA
archaeo_mag-0.0.1.dist-info/WHEEL
archaeo_mag-0.0.1.dist-info/top_level.txt
archaeo_mag-0.0.1.dist-info/RECORD
