Metadata-Version: 2.1
Name: archaeo-mag
Version: 0.0.1
Summary: A package for magnetometry data processing.
Home-page: https://github.com/jgmenzer/archaeo-mag
Author: Jeremy G. Menzer
Author-email: jeremy.menzer@gmail.com
License: UNKNOWN
Project-URL: Bug Tracker, https://github.com/jgmenzer/archaeo-mag/issues
Platform: UNKNOWN
Classifier: Programming Language :: Python :: 3.8
Classifier: License :: OSI Approved :: MIT License
Classifier: Operating System :: Microsoft :: Windows :: Windows 7
Classifier: Development Status :: 3 - Alpha
Requires-Python: >=3.8
License-File: LICENSE
